{
  "extends": ["config:best-practices"],
  "semanticCommits": "enabled",
  "prConcurrentLimit": 5,
  "labels": ["dependencies"],
  "packageRules": [
    {
      "matchUpdateTypes": ["patch"],
      "enabled": false,
    },
    {
      "matchSourceUrls": ["https://github.com/triggerdotdev/trigger.dev"],
      "groupName": "trigger.dev monorepo packages"
    },
    {
      "description": "Group all NatchOS packages together",
      "groupName": "NatchOS",
      "patch": {
        "enabled": true
      },
      "matchPackageNames": [
        "NatchOS.{/,}**"
      ]
    },
    {
      "description": "Group all NatchCms packages together",
      "groupName": "NatchCms",
      "patch": {
        "enabled": true
      },
      "matchPackageNames": [
        "NatchCms.{/,}**"
      ]
    },
    {
      "description": "Group all Natch packages together",
      "groupName": "Natch",
      "patch": {
        "enabled": true
      },
      "matchPackageNames": [
        "Natch.{/,}**"
      ]
    }
  ],
  "timezone": "CET",
  "schedule": [
    "* 0-4,22-23 * * 1-5",
    "* * * * 0,6"
  ],
  "abandonmentThreshold": "2 years"
}
